LICENSE
MANIFEST.in
README.md
setup.cfg
setup.py
./.gitignore
./CMakeLists.txt
./CONTRIBUTING.md
./CONTRIBUTORS.md
./INSTALL.md
./LICENSE
./MANIFEST.in
./Makefile
./Makefile.config
./Makefile.config.example
./README.md
./caffe.cloc
./setup.cfg
./setup.py
./.git/FETCH_HEAD
./.git/HEAD
./.git/config
./.git/description
./.git/index
./.git/shallow
./.git/hooks/applypatch-msg.sample
./.git/hooks/commit-msg.sample
./.git/hooks/fsmonitor-watchman.sample
./.git/hooks/post-update.sample
./.git/hooks/pre-applypatch.sample
./.git/hooks/pre-commit.sample
./.git/hooks/pre-merge-commit.sample
./.git/hooks/pre-push.sample
./.git/hooks/pre-rebase.sample
./.git/hooks/pre-receive.sample
./.git/hooks/prepare-commit-msg.sample
./.git/hooks/push-to-checkout.sample
./.git/hooks/sendemail-validate.sample
./.git/hooks/update.sample
./.git/info/exclude
./.git/logs/HEAD
./.git/objects/pack/pack-08e834433c9408b674972e19ae5325cb94219ea0.idx
./.git/objects/pack/pack-08e834433c9408b674972e19ae5325cb94219ea0.pack
./.git/objects/pack/pack-08e834433c9408b674972e19ae5325cb94219ea0.rev
./.git/refs/tags/v9.0.2
./.github/workflows/python-publish.yml
./cmake/ConfigGen.cmake
./cmake/Cuda.cmake
./cmake/Dependencies.cmake
./cmake/Misc.cmake
./cmake/ProtoBuf.cmake
./cmake/Summary.cmake
./cmake/Targets.cmake
./cmake/Uninstall.cmake.in
./cmake/Utils.cmake
./cmake/lint.cmake
./cmake/External/gflags.cmake
./cmake/External/glog.cmake
./cmake/Modules/FindAtlas.cmake
./cmake/Modules/FindGFlags.cmake
./cmake/Modules/FindGlog.cmake
./cmake/Modules/FindLAPACK.cmake
./cmake/Modules/FindLMDB.cmake
./cmake/Modules/FindLevelDB.cmake
./cmake/Modules/FindMKL.cmake
./cmake/Modules/FindMatlabMex.cmake
./cmake/Modules/FindNCCL.cmake
./cmake/Modules/FindNumPy.cmake
./cmake/Modules/FindOpenBLAS.cmake
./cmake/Modules/FindSnappy.cmake
./cmake/Modules/FindvecLib.cmake
./cmake/Templates/CaffeConfig.cmake.in
./cmake/Templates/CaffeConfigVersion.cmake.in
./cmake/Templates/caffe_config.h.in
./data/cifar10/get_cifar10.sh
./python/brocolli_caffe.egg-info/PKG-INFO
./python/brocolli_caffe.egg-info/SOURCES.txt
./python/brocolli_caffe.egg-info/dependency_links.txt
./python/brocolli_caffe.egg-info/not-zip-safe
./python/brocolli_caffe.egg-info/top_level.txt
python/brocolli_caffe.egg-info/PKG-INFO
python/brocolli_caffe.egg-info/SOURCES.txt
python/brocolli_caffe.egg-info/dependency_links.txt
python/brocolli_caffe.egg-info/not-zip-safe
python/brocolli_caffe.egg-info/top_level.txt
